README.md
setup.py
hedgeguy/__init__.py
hedgeguy/hedgeguy_Aggregate.py
hedgeguy/hedgeguy_Components.py
hedgeguy/hedgeguy_EquityCurves.py
hedgeguy.egg-info/PKG-INFO
hedgeguy.egg-info/SOURCES.txt
hedgeguy.egg-info/dependency_links.txt
hedgeguy.egg-info/requires.txt
hedgeguy.egg-info/top_level.txt