Metadata-Version: 2.1
Name: hedgeguy
Version: 1.0.1
Summary: Hedgeguy
Home-page: https://pypi.org/project/plotguy/
Author: Plotguy Team
Author-email: plotguy.info@gmail.com
License: UNKNOWN
Platform: UNKNOWN
Classifier: Programming Language :: Python :: 3
Classifier: Operating System :: OS Independent
